stardist_napari/__init__.py
stardist_napari/_dock_widget.py
stardist_napari/_sample_data.py
stardist_napari/_version.py
stardist_napari/napari.yaml
stardist_napari/_tests/__init__.py
stardist_napari/_tests/conftest.py
stardist_napari/_tests/test_run.py
stardist_napari/_tests/test_samples.py
stardist_napari/_tests/test_ui.py
stardist_napari/resources/stardist_logo_napari.png
stardist_napari-2024.8.6.1.dist-info/LICENSE.txt
stardist_napari-2024.8.6.1.dist-info/METADATA
stardist_napari-2024.8.6.1.dist-info/WHEEL
stardist_napari-2024.8.6.1.dist-info/entry_points.txt
stardist_napari-2024.8.6.1.dist-info/top_level.txt
stardist_napari-2024.8.6.1.dist-info/RECORD
