Metadata-Version: 2.1
Name: stardist-napari
Version: 2024.8.6.1
Summary: Object Detection with Star-convex Shapes
Home-page: https://github.com/stardist/stardist
Author: Uwe Schmidt, Martin Weigert
Author-email: research@uweschmidt.org, martin.weigert@epfl.ch
License: BSD 3-Clause License
Project-URL: Source Code, https://github.com/stardist/stardist-napari
Project-URL: Documentation, https://github.com/stardist/stardist-napari
Project-URL: Bug Tracker, https://github.com/stardist/stardist-napari/issues
Project-URL: User Support, https://forum.image.sc/tag/stardist
Project-URL: Twitter, https://twitter.com/martweig
Classifier: Development Status :: 4 - Beta
Classifier: Intended Audience :: Science/Research
Classifier: Topic :: Scientific/Engineering
Classifier: License :: OSI Approved :: BSD License
Classifier: Operating System :: OS Independent
Classifier: Programming Language :: Python :: 3.8
Classifier: Programming Language :: Python :: 3.9
Classifier: Programming Language :: Python :: 3.10
Classifier: Programming Language :: Python :: 3.11
Classifier: Framework :: napari
Requires-Python: >=3.8
License-File: LICENSE.txt
Requires-Dist: stardist>=0.8.3
Requires-Dist: napari>=0.4.13
Requires-Dist: magicgui>=0.4.0
Requires-Dist: tensorflow; platform_system != "Darwin" or platform_machine != "arm64"
Requires-Dist: tensorflow-macos; platform_system == "Darwin" and platform_machine == "arm64"
Requires-Dist: tensorflow-metal; platform_system == "Darwin" and platform_machine == "arm64"
Provides-Extra: test
Requires-Dist: pytest; extra == "test"
Requires-Dist: pytest-qt; extra == "test"
Requires-Dist: napari[pyqt]>=0.4.13; extra == "test"
